bin/__init__.py
bin/compile_models.py
bin/dsreg.py
bin/dsreg_plot.py
bin/reg_enrichment.py
dSreg/__init__.py
dSreg/dsreg_fit.py
dSreg/models/__init__.py
dSreg/models/stan_models.py
dSreg/models/compiled/dS-PW.p
dSreg/models/compiled/dSreg-PW.p
dSreg/models/stan_code/dS-PW.stan
dSreg/models/stan_code/dSreg-PW.stan
dSreg/models/stan_code/dSreg-PW2.stan
dSreg/models/stan_code/dSreg-Sigmoid.stan
dSreg/models/stan_code/dSreg-TS.stan
dSreg/models/stan_code/gp_scale_prior.stan
dSreg/utils/__init__.py
dSreg/utils/event_counts.py
dSreg/utils/plots.py
dSreg/utils/settings.py
dSreg/utils/utils.py
dSreg-1.0.0.dist-info/LICENSE
dSreg-1.0.0.dist-info/METADATA
dSreg-1.0.0.dist-info/WHEEL
dSreg-1.0.0.dist-info/entry_points.txt
dSreg-1.0.0.dist-info/top_level.txt
dSreg-1.0.0.dist-info/RECORD
