Metadata-Version: 2.1
Name: dSreg
Version: 1.0.0
Summary: Joint inference of alternative splicing and regulatory changes
Home-page: https://bitbucket.org/cmartiga/dSreg
Author: UNKNOWN
Author-email: cmarti@cnic.es
License: UNKNOWN
Keywords: bioinformatics,Splicing regulation,alternative splicing,RNA-Seq,probabilistic models,bayesian
Platform: ALL
Classifier: Programming Language :: Python :: 3
Classifier: Intended Audience :: Science/Research
Classifier: License :: OSI Approved :: MIT License
Classifier: Operating System :: OS Independent
Requires-Dist: pystan (==2.18.0.0)
Requires-Dist: statsmodels (==0.10.1)
Requires-Dist: seaborn (==0.9.0)
Requires-Dist: matplotlib (==3.1.0)
Requires-Dist: scipy (==1.3.0)
Requires-Dist: pandas (==0.25.0)
